doc/conf.py
examples/client.py
linalgo/__init__.py
linalgo/__main__.py
linalgo/config.py
linalgo/annotate/__init__.py
linalgo/annotate/bounding_box.py
linalgo/annotate/display.py
linalgo/annotate/models.py
linalgo/annotate/serializers.py
linalgo/annotate/transformers.py
linalgo/annotate/utils.py
linalgo/annotate/test/__init__.py
linalgo/annotate/test/fixtures.py
linalgo/annotate/test/test_bounding_box.py
linalgo/annotate/test/test_models.py
linalgo/annotate/test/test_transformers.py
linalgo/annotate/test/test_utils.py
linalgo/hub/__init__.py
linalgo/hub/bq_client.py
linalgo/hub/client.py
linalgo/hub/scheduler.py
linalgo/tests/test_schedule.py
linalgo-0.1.6.dist-info/licenses/LICENSE
linalgo-0.1.6.dist-info/METADATA
linalgo-0.1.6.dist-info/WHEEL
linalgo-0.1.6.dist-info/entry_points.txt
linalgo-0.1.6.dist-info/top_level.txt
linalgo-0.1.6.dist-info/RECORD
