Metadata-Version: 2.4
Name: linalgo
Version: 0.1.6
Summary: W3C Data Annotation for Natual Language Processing and Machine Leaning in Python.
Author-email: Arnaud Rachez <arnaud@linalgo.com>
Project-URL: Homepage, https://github.com/linalgo/linalgo
Project-URL: Bug Reports, https://github.com/linalgo/linalgo/issues
Project-URL: Source, https://github.com/linalgo/linalgo
License-File: LICENSE
Requires-Dist: ipython
Requires-Dist: google-cloud
Requires-Dist: google-cloud-bigquery
Requires-Dist: numpy
Requires-Dist: pillow
Requires-Dist: python-dateutil
Requires-Dist: requests
Requires-Dist: typer==0.15.3
Requires-Dist: click==8.1.3
Provides-Extra: hub
Requires-Dist: linhub; extra == "hub"
Dynamic: license-file
